python_workspace/__init__.py
python_workspace/main.py
python_workspace/parallel_exec.py
python_workspace/project.py
python_workspace/project_command_sources.py
python_workspace/workspace.py
python_workspace-1.0.3.dist-info/LICENSE
python_workspace-1.0.3.dist-info/METADATA
python_workspace-1.0.3.dist-info/WHEEL
python_workspace-1.0.3.dist-info/entry_points.txt
python_workspace-1.0.3.dist-info/RECORD
